setup.cfg
setup.py
PyQtMapManager/__init__.py
PyQtMapManager/main.py
PyQtMapManager/mmApp.py
PyQtMapManager/mmCanvas.py
PyQtMapManager/mmTable.py
PyQtMapManager/mmWindow.py
pymapmanager/__init__.py
pymapmanager/mmMap.py
pymapmanager/mmMapAnalysis.py
pymapmanager/mmMapPlot2.py
pymapmanager/mmMapPool.py
pymapmanager/mmStack.py
pymapmanager/mmStackLine.py
pymapmanager/mmStackPool.py
pymapmanager/mmUtil.py
pymapmanager/mmio.py
pymapmanager/version.py
pymapmanager.egg-info/PKG-INFO
pymapmanager.egg-info/SOURCES.txt
pymapmanager.egg-info/dependency_links.txt
pymapmanager.egg-info/requires.txt
pymapmanager.egg-info/top_level.txt
test/test_pymapmanager.py