Metadata-Version: 1.0
Name: pymapmanager
Version: 0.0.5
Summary: Load, analyze, and visualize Map Manager files
Home-page: http://github.com/cudmore/PyMapManager
Author: Robert H Cudmore
Author-email: robert.cudmore@gmail.com
License: MIT
Platform: UNKNOWN
